config.template.toml
serverctl/__init__.py
serverctl/config.py
serverctl/daemon.py
serverctl/main.py
serverctl/server.py
serverctl/util.py
serverctl.service
serverctl@.service
serverctl-0.2.8.dist-info/METADATA
serverctl-0.2.8.dist-info/WHEEL
serverctl-0.2.8.dist-info/entry_points.txt
serverctl-0.2.8.dist-info/RECORD
