Metadata-Version: 2.1
Name: serverctl
Version: 0.2.8
Summary: 
Author: Wenyu Zhao
Author-email: wenyuzhaox@gmail.com
Requires-Python: >=3.10,<4.0
Classifier: Programming Language :: Python :: 3
Classifier: Programming Language :: Python :: 3.10
Classifier: Programming Language :: Python :: 3.11
Classifier: Programming Language :: Python :: 3.12
Requires-Dist: tosholi (>=0.1.0,<0.2.0)
Requires-Dist: typer (>=0.12.3,<0.13.0)
